elisa_patch
