Metadata-Version: 2.1
Name: elisa-patch
Version: 0.3.2
Summary: Dictionary incorporation for machine translation
Home-page: https://github.com/ChenghaoMou/elisa-patch
Author: chenghaomou
Author-email: chengham@isi.edu
License: UNKNOWN
Platform: UNKNOWN
Classifier: Development Status :: 4 - Beta
Classifier: Intended Audience :: Developers
Classifier: License :: OSI Approved :: MIT License
Classifier: Programming Language :: Python :: 3.7
